fleet/__init__.py
fleet/version.py
fleet/dataset/__init__.py
fleet/dataset/dataset_base.py
fleet/infer/__init__.py
fleet/infer/infer_base.py
fleet/models/__init__.py
fleet/models/input_maker.py
fleet/models/model_base.py
fleet/optimizer/__init__.py
fleet/optimizer/optimizer_base.py
fleet/submit_client/__init__.py
fleet/submit_client/client_base.py
fleet/trainer/__init__.py
fleet/trainer/trainer_base.py
fleet/utils/__init__.py
fleet/utils/hdfs.py
fleet/utils/system_info.py
paddle_fleet-0.1.1.dist-info/DESCRIPTION.rst
paddle_fleet-0.1.1.dist-info/METADATA
paddle_fleet-0.1.1.dist-info/RECORD
paddle_fleet-0.1.1.dist-info/WHEEL
paddle_fleet-0.1.1.dist-info/metadata.json
paddle_fleet-0.1.1.dist-info/top_level.txt
